_rei.cpython-38-darwin.so
rei/__init__.py
rei-0.0.0.dist-info/METADATA
rei-0.0.0.dist-info/WHEEL
rei-0.0.0.dist-info/top_level.txt
rei-0.0.0.dist-info/RECORD
